tt4l/__init__.py
tt4l/cli/__init__.py
tt4l/cli/default_arguments.py
tt4l/cli/inference.py
tt4l/cli/main.py
tt4l/cli/utils.py
tt4l/factory/__init__.py
tt4l/factory/auto.py
tt4l/factory/base/__init__.py
tt4l/factory/base/arguments.py
tt4l/factory/base/data_process.py
tt4l/factory/base/factory.py
tt4l/factory/text_classification/__init__.py
tt4l/factory/text_classification/arguments.py
tt4l/factory/text_classification/data.py
tt4l/factory/text_classification/factory.py
tt4l/factory/token_classification/__init__.py
tt4l/factory/token_classification/arguments.py
tt4l/factory/token_classification/data.py
tt4l/factory/token_classification/factory.py
tt4l/factory/token_classification/utils.py
tt4l/factory/universal_information_extraction/__init__.py
tt4l/factory/universal_information_extraction/arguments.py
tt4l/factory/universal_information_extraction/data.py
tt4l/factory/universal_information_extraction/factory.py
tt4l/factory/universal_information_extraction/modules.py
tt4l/functional/__init__.py
tt4l/functional/numpy.py
tt4l/layers/__init__.py
tt4l/layers/encoder/__init__.py
tt4l/layers/encoder/position.py
tt4l/layers/pointer/__init__.py
tt4l/layers/pointer/global_pointer.py
tt4l/layers/pointer/span.py
tt4l/layers/pooling/__init__.py
tt4l/layers/pooling/last_hidden_states_pooling.py
tt4l/layers/pooling/utils.py
tt4l/layers/sequence/__init__.py
tt4l/layers/sequence/crf.py
tt4l/loss/__init__.py
tt4l/loss/multi_label_categorical_cross_entropy.py
tt4l/metrics/__init__.py
tt4l/metrics/base.py
tt4l/metrics/compute/__init__.py
tt4l/metrics/compute/text_classification.py
tt4l/metrics/compute/token_classification.py
tt4l/metrics/compute/universal_information_extraction.py
tt4l/metrics/evaluate/__init__.py
tt4l/metrics/evaluate/accuracy.py
tt4l/metrics/evaluate/f1.py
tt4l/metrics/evaluate/mse.py
tt4l/metrics/evaluate/seqeval.py
tt4l/modeling_outputs.py
tt4l/models/__init__.py
tt4l/models/modeling_bert.py
tt4l/models/modeling_ernie.py
tt4l/optimizer_builder.py
tt4l-0.0.4.dist-info/LICENSE
tt4l-0.0.4.dist-info/METADATA
tt4l-0.0.4.dist-info/WHEEL
tt4l-0.0.4.dist-info/entry_points.txt
tt4l-0.0.4.dist-info/RECORD
