Metadata-Version: 2.1
Name: tt4l
Version: 0.0.4
Summary: Training a transformer model for language
Home-page: https://github.com/fjklqq/tt4l
License: Apache-2.0
Author: ZhouHang
Author-email: fjklqq@gmail.com
Requires-Python: >=3.10,<4.0
Classifier: License :: OSI Approved :: Apache Software License
Classifier: Programming Language :: Python :: 3
Classifier: Programming Language :: Python :: 3.10
Classifier: Programming Language :: Python :: 3.11
Classifier: Programming Language :: Python :: 3.12
Classifier: Programming Language :: Python :: 3.13
Requires-Dist: accelerate (>=0.34.0,<=1.0.1)
Requires-Dist: datasets (>=2.17.0,<3.0.0)
Requires-Dist: evaluate (>=0.4.2,<0.5.0)
Requires-Dist: matplotlib (>=3.9.2,<4.0.0)
Requires-Dist: pydantic (>=2.6.0,<3.0.0)
Requires-Dist: scikit-learn (>=1.4.0,<2.0.0)
Requires-Dist: seqeval (>=1.2.2,<2.0.0)
Requires-Dist: torch (>=2.1.0,<3.0.0)
Requires-Dist: transformers (>=4.41.2,<=4.46.1)
Requires-Dist: typer (>=0.12.3,<0.13.0)
